device_server/__init__.py
device_server/device_server.py
device_server/rpc_mixin.py
device_server/cli/__init__.py
device_server/cli/launch.py
device_server/devices/__init__.py
device_server/devices/config_update_handler.py
device_server/devices/device_serializer.py
device_server/devices/devicemanager.py
bec_device_server-1.24.1.dist-info/METADATA
bec_device_server-1.24.1.dist-info/WHEEL
bec_device_server-1.24.1.dist-info/entry_points.txt
bec_device_server-1.24.1.dist-info/top_level.txt
bec_device_server-1.24.1.dist-info/RECORD
